_qlip_serve_generator_dummy_ext.cpython-311-x86_64-linux-gnu.so
qlip_serve/generator/__init__.py
qlip_serve/generator/generator.py
qlip_serve/generator/template.py
qlip_serve/generator/utils.py
qlip_serve/generator/pyarmor_runtime_008031/__init__.py
qlip_serve/generator/pyarmor_runtime_008031/pyarmor_runtime.so
qlip_serve_generator-0.1.17.dist-info/METADATA
qlip_serve_generator-0.1.17.dist-info/WHEEL
qlip_serve_generator-0.1.17.dist-info/top_level.txt
qlip_serve_generator-0.1.17.dist-info/RECORD
