Metadata-Version: 2.4
Name: qlip-serve-generator
Version: 0.1.17
Requires-Dist: Cython>=3.0.8
Requires-Dist: setuptools>=72.1.0
Requires-Dist: qlip-serve-common==0.1.17
Dynamic: requires-dist
